README.rst
setup.py
range_regex/__init__.py
range_regex/range_regex.py
range_regex/tests.py
range_regex.egg-info/PKG-INFO
range_regex.egg-info/SOURCES.txt
range_regex.egg-info/dependency_links.txt
range_regex.egg-info/top_level.txt