Metadata-Version: 1.0
Name: range-regex
Version: 1.0.4
Summary: Python numeric range regular expression generator
Home-page: http://github.com/dimka665/range-regex
Author: Dmitry Voronin
Author-email: dimka665@gmail.com
License: BSD
Keywords: numeric range regex regular expression generator
Platform: UNKNOWN
